menyou/__init__.py
menyou/menyou.py
menyou-1.0.dist-info/LICENSE.TXT
menyou-1.0.dist-info/METADATA
menyou-1.0.dist-info/WHEEL
menyou-1.0.dist-info/top_level.txt
menyou-1.0.dist-info/RECORD
