Metadata-Version: 2.1
Name: menyou
Version: 1.0
Summary: A easy-to-use console-based menu.
Home-page: https://gitlab.com/ricoflow/menyou
Author: Randall Speake
Author-email: ranspeake@gmail.com
License: License :: OSI Approved :: GNU General Public License v3 (GPLv3)
Platform: UNKNOWN
Requires-Python: >=3.6
Requires-Dist: pyfiglet
